syncpg.py
syncpg-1.1.2.dist-info/LICENSE.md
syncpg-1.1.2.dist-info/METADATA
syncpg-1.1.2.dist-info/WHEEL
syncpg-1.1.2.dist-info/top_level.txt
syncpg-1.1.2.dist-info/RECORD
