Metadata-Version: 2.1
Name: syncpg
Version: 1.1.2
Summary: synchronous wrapper for asyncpg
Home-page: https://github.com/iomintz/syncpg
Author: iomintz
Author-email: io@mintz.cc
License: BlueOak-1.0.0
Platform: UNKNOWN
Classifier: Topic :: Software Development
Classifier: Topic :: Database :: Front-Ends
Classifier: Development Status :: 5 - Production/Stable
Classifier: Programming Language :: Python :: 3 :: Only
Classifier: Programming Language :: Python :: 3.5
Classifier: Programming Language :: Python :: 3.6
Classifier: Programming Language :: Python :: 3.7
Classifier: Programming Language :: Python :: 3.8
